yasiu_image/__init__.py
yasiu_image/common.py
yasiu_image/convolve.py
yasiu_image/features.py
yasiu_image/filters.py
yasiu_image/io.py
yasiu_image/modifiers.py
yasiu_image/quality.py
yasiu_image-0.3.1.dist-info/licenses/LICENSE
yasiu_image-0.3.1.dist-info/METADATA
yasiu_image-0.3.1.dist-info/WHEEL
yasiu_image-0.3.1.dist-info/top_level.txt
yasiu_image-0.3.1.dist-info/RECORD
